sasrl_env/__init__.py
sasrl_env/client.py
sasrl_env/runClient.py
sasrl_env/runServer.py
sasrl_env/serverSingle.py
sasrl_env/common/__init__.py
sasrl_env/common/atari_wrappers.py
sasrl_env/common/env_pb2.py
sasrl_env/common/env_pb2_grpc.py
sasrl_env/common/utils.py
sasrl_env/common/wrapper.py
sasrl_env/utils/__init__.py
sasrl_env/utils/utils.py
sasrl_env-1.2.0.dist-info/LICENSE
sasrl_env-1.2.0.dist-info/METADATA
sasrl_env-1.2.0.dist-info/WHEEL
sasrl_env-1.2.0.dist-info/top_level.txt
sasrl_env-1.2.0.dist-info/RECORD
