Metadata-Version: 2.1
Name: sasrl-env
Version: 1.2.0
Summary: Generate protobuf files in python and C++ to be used for remote access to RL environment
Home-page: https://gitlab.sas.com/RezaNazari/rlenv_grpc.git
Author: SAS
Author-email: support@sas.com
License: Apache 2.0
Classifier: Programming Language :: Python :: 3
Classifier: Operating System :: OS Independent
Requires-Python: >=3.7
License-File: LICENSE
Requires-Dist: grpcio (>=1.50.0)
Requires-Dist: protobuf (>=4.21.9)
Requires-Dist: gym (>=0.26.2)
